pa_math/__init__.py
pa_math/paMathExcel2json.py
pa_math_liuxinglu-0.0.1.dist-info/LICENSE
pa_math_liuxinglu-0.0.1.dist-info/METADATA
pa_math_liuxinglu-0.0.1.dist-info/WHEEL
pa_math_liuxinglu-0.0.1.dist-info/top_level.txt
pa_math_liuxinglu-0.0.1.dist-info/RECORD
