Metadata-Version: 2.1
Name: pa-math-liuxinglu
Version: 0.0.1
Summary: 数学部测试成绩转换专用工具
Home-page: https://github.com/liuxinglu/pa_math
Author: liuxinglu
Author-email: liuxinglu675@sina.com
License: MIT
Platform: UNKNOWN
Classifier: Programming Language :: Python :: 3
Classifier: License :: OSI Approved :: MIT License
Classifier: Operating System :: OS Independent
Requires-Python: >=3.6
Requires-Dist: openpyxl (>=3.0.5)
Requires-Dist: xlrd (>=1.2.0)
